gpu_sentinel/BUILD
gpu_sentinel/__init__.py
gpu_sentinel/main.py
gpu_sentinel/sentinel.py
gpu_sentinel/sentinel_test.py
gpu_sentinel-0.1.4.dist-info/METADATA
gpu_sentinel-0.1.4.dist-info/WHEEL
gpu_sentinel-0.1.4.dist-info/entry_points.txt
gpu_sentinel-0.1.4.dist-info/licenses/LICENSE
gpu_sentinel-0.1.4.dist-info/RECORD
