Metadata-Version: 2.1
Name: gpu_sentinel
Version: 0.1.4
Summary: Monitor idle GPU usage.
Project-URL: Homepage, https://github.com/moonshinelabs/gpu_sentinel
Author-email: Nate Harada <gpu_sentinel@moonshinelabs.ai>
License: MIT
License-File: LICENSE
Keywords: gpu,monitor,utilization
Classifier: License :: OSI Approved :: MIT License
Classifier: Programming Language :: Python :: 3
Requires-Python: >=3.7
Requires-Dist: gputil
